{
  "sections": {
    "ds-cc-base": {
      "type": "ds-cc-base",
      "blocks": {
        "tile-lateral-files": {
          "type": "tile",
          "settings": {
            "title": "Lateral Filing Cabinets",
            "link": "/collections/lateral-file-cabinets-storage",
            "description": "Wide-format lateral files for high-volume document storage."
          }
        },
        "tile-vertical-files": {
          "type": "tile",
          "settings": {
            "title": "Vertical Filing Cabinets",
            "link": "/collections/vertical-file-cabinets-storage",
            "description": "Standard vertical files in 2, 3, and 4-drawer configurations."
          }
        },
        "tile-pedestals": {
          "type": "tile",
          "settings": {
            "title": "Mobile Pedestals",
            "link": "/collections/mobile-pedestals",
            "description": "Under-desk rolling pedestals for workstation storage."
          }
        },
        "tile-storage-cabinets": {
          "type": "tile",
          "settings": {
            "title": "Storage Cabinets",
            "link": "/collections/storage-cabinets",
            "description": "Tall and half-height storage cabinets with locking doors."
          }
        },
        "tile-bookcases": {
          "type": "tile",
          "settings": {
            "title": "Bookcases & Shelving",
            "link": "/collections/bookcases",
            "description": "Open bookcases and adjustable shelving units."
          }
        },
        "tile-lockers": {
          "type": "tile",
          "settings": {
            "title": "Lockers",
            "link": "/collections/lockers",
            "description": "Personal storage lockers for shared and open-plan environments."
          }
        },
        "tile-credenzas": {
          "type": "tile",
          "settings": {
            "title": "Credenzas",
            "link": "/collections/credenzas",
            "description": "Low-profile storage credenzas for offices and boardrooms."
          }
        },
        "tile-mailboxes": {
          "type": "tile",
          "settings": {
            "title": "Mailboxes & Sorters",
            "link": "/collections/mailboxes",
            "description": "Mail sorters and distribution units for shared facilities."
          }
        },
        "tile-wardrobe": {
          "type": "tile",
          "settings": {
            "title": "Wardrobe Storage",
            "link": "/collections/wardrobe-storage",
            "description": "Wardrobe cabinets and coat storage for offices and reception."
          }
        },
        "tile-media-storage": {
          "type": "tile",
          "settings": {
            "title": "Media & AV Storage",
            "link": "/collections/media-storage",
            "description": "TV stands, media consoles, and AV storage furniture."
          }
        },
        "tile-mobile-storage": {
          "type": "tile",
          "settings": {
            "title": "Mobile Storage Carts",
            "link": "/collections/mobile-storage",
            "description": "Rolling storage carts and utility carts for flexible spaces."
          }
        },
        "tile-wall-storage": {
          "type": "tile",
          "settings": {
            "title": "Wall-Mounted Storage",
            "link": "/collections/wall-storage",
            "description": "Wall-mounted shelving and storage solutions."
          }
        },
        "tile-personal-lockers": {
          "type": "tile",
          "settings": {
            "title": "Personal Storage",
            "link": "/collections/personal-storage",
            "description": "Desk-top organizers, trays, and personal storage accessories."
          }
        },
        "tile-high-density": {
          "type": "tile",
          "settings": {
            "title": "High-Density Storage",
            "link": "/collections/high-density-storage",
            "description": "Compact shelving and high-density storage systems."
          }
        },
        "brand-plate-1": {
          "type": "brand_plate",
          "settings": {
            "brand_plate_name": "ergoCentric",
            "brand_plate_link": "/pages/brands#ergocentric",
            "brand_plate_canadian": true
          }
        },
        "brand-plate-2": {
          "type": "brand_plate",
          "settings": {
            "brand_plate_name": "Keilhauer",
            "brand_plate_link": "/pages/brands#keilhauer",
            "brand_plate_canadian": true
          }
        },
        "brand-plate-3": {
          "type": "brand_plate",
          "settings": {
            "brand_plate_name": "Global Furniture",
            "brand_plate_link": "/pages/brands#global-furniture",
            "brand_plate_canadian": false
          }
        },
        "brand-plate-4": {
          "type": "brand_plate",
          "settings": {
            "brand_plate_name": "Teknion",
            "brand_plate_link": "/pages/brands#teknion",
            "brand_plate_canadian": false
          }
        }
      },
      "block_order": [
        "tile-lateral-files",
        "tile-vertical-files",
        "tile-pedestals",
        "tile-storage-cabinets",
        "tile-bookcases",
        "tile-lockers",
        "tile-credenzas",
        "tile-mailboxes",
        "tile-wardrobe",
        "tile-media-storage",
        "tile-mobile-storage",
        "tile-wall-storage",
        "tile-personal-lockers",
        "tile-high-density",
        "brand-plate-1",
        "brand-plate-2",
        "brand-plate-3",
        "brand-plate-4"
      ],
      "settings": {
        "logo": "shopify://shop_images/bbi-logo-v2_aa647658-6557-4dc8-abb7-f20f7b4c4a03.png",
        "breadcrumb_parent_label": "Business Furniture",
        "breadcrumb_parent_url": "/collections/business-furniture",
        "hero_title": "Storage & Filing",
        "hero_subtitle": "Commercial filing and storage for Ontario institutions — lateral files, lockers, credenzas, and high-density systems. OECM-eligible.",
        "cta_label": "",
        "intro_text": "<p>From 2-drawer pedestals to floor-to-ceiling high-density systems — Brant Business Interiors carries every storage format required by schools, government offices, and healthcare facilities. OECM Agreement 2025-470 covers the full storage line. Quote in 1 business day.</p>",
        "show_view_all_cta": true,
        "view_all_label": "View all storage",
        "show_phone_cta": true,
        "phone_cta_label": "Talk to a storage specialist",
        "grid_mode": "both",
        "products_per_page": 12,
        "show_sector_bar": true,
        "show_brands_band": true,
        "show_filter_chips": true
      }
    }
  },
  "order": [
    "ds-cc-base"
  ]
}
