{
  "handle": "l-shape-desk-hutch",
  "title": "L-Shape Desk & Hutch",
  "hero_rank": 2,
  "brand_hint": "Brand unknown — search title to identify manufacturer",
  "specs": {
    "confidence": "none",
    "source_urls": [],
    "manufacturer": "",
    "product_line": "",
    "model_codes": [],
    "dimensions": "",
    "weight": "",
    "weight_capacity": "",
    "materials": "",
    "finishes_available": [],
    "key_features": [],
    "certifications": [],
    "warranty": "",
    "country_of_manufacture": "",
    "notes": "Product title 'L-Shape Desk & Hutch' contains no model code, brand name, or distinguishing product line identifier. Cannot reliably map to a specific manufacturer SKU from BBI's typical catalog (Global Furniture Group, OTG/Offices to Go, ObusForme). Both Global (e.g. Zira, Genoa, Princeton) and OTG (e.g. Superior Laminate, Ionic) offer L-shape desk + hutch configurations under many SKUs, so guessing would fabricate data. Recommend BBI supply the model code, SKU, or a product image/URL for accurate spec lookup."
  },
  "usage": {
    "input_tokens": 8478,
    "output_tokens": 407,
    "cache_creation_input_tokens": 0,
    "cache_read_input_tokens": 0
  },
  "fetched_at": "2026-04-20T22:26:45-0400"
}