{
  "handle": "napa-boardroom-conference-table",
  "title": "Napa Boardroom Conference Table",
  "hero_rank": 60,
  "brand_hint": "Office Star Napa series (NOT Global)",
  "specs": {
    "confidence": "low",
    "source_urls": [
      "https://newmarketofficefurniture.com/product-category/new-products/napa/napa-series-boardroom-tables/",
      "https://www.nationalbusinessfurniture.com/napa-four-seat-round-conference-table-42dia-46184"
    ],
    "manufacturer": "Office Star (Napa series)",
    "product_line": "Napa Boardroom Tables",
    "model_codes": [],
    "dimensions": "",
    "weight": "",
    "weight_capacity": "",
    "materials": "Engineered wood top with laminate finish, 3mm PVC tri-groove edge banding",
    "finishes_available": [],
    "key_features": [
      "X-base or pedestal conference table",
      "3mm PVC edge with tri-groove damage-resistance pattern",
      "Available in multiple sizes (4-seat to large boardroom)"
    ],
    "certifications": [],
    "warranty": "",
    "country_of_manufacture": "",
    "notes": "Confirmed Napa is an Office Star line, not Global. Per-size dimensions on retailer pages (Newmarket Office Furniture, National Business Furniture) — verify exact BBI SKU."
  },
  "usage": {
    "input_tokens": 0,
    "output_tokens": 0,
    "cache_creation_input_tokens": 0,
    "cache_read_input_tokens": 0
  },
  "fetched_at": "2026-05-02T17:23:33-0400"
}